[
    {
        "name": "Reverse Words in a String",
        "tags": [
            "string",
            "string manipulation",
            "word reversal",
            "tokenization"
        ],
        "platforms": [
            "LeetCode"
        ],
        "level": "Easy",
        "link": "https://leetcode.com/problems/reverse-words-in-a-string/"
    },
    {
        "name": "Remove Outermost Parentheses",
        "tags": [
            "string",
            "stack",
            "parentheses manipulation",
            "substring extraction"
        ],
        "platforms": [
            "LeetCode"
        ],
        "level": "Easy",
        "link": "https://leetcode.com/problems/remove-outermost-parentheses/"
    },
    {
        "name": "Two Sum",
        "tags": [
            "Array",
            "Hash Table"
        ],
        "platforms": [
            "LeetCode"
        ],
        "level": "Easy",
        "link": "https://leetcode.com/problems/two-sum/"
    },
    {
        "name": "Sum of All Odd Length Subarrays",
        "tags": [
            "array",
            "subarray sum",
            "odd length subarrays",
            "combinatorics"
        ],
        "platforms": [
            "LeetCode"
        ],
        "level": "Easy",
        "link": "https://leetcode.com/problems/sum-of-all-odd-length-subarrays/"
    },
    {
        "name": "Reverse Integer",
        "tags": [
            "math"
        ],
        "platforms": [
            "LeetCode"
        ],
        "level": "Easy",
        "link": "https://leetcode.com/problems/reverse-integer/"
    },
    {
        "name": "Implement strStr()",
        "tags": [
            "string",
            "searching",
            "algorithm"
        ],
        "platforms": [
            "LeetCode"
        ],
        "level": "Easy",
        "link": "https://leetcode.com/problems/implement-strstr/"
    },
    {
        "name": "Richest Customer Wealth",
        "tags": [
            "array",
            "wealth calculation",
            "element sum",
            "richness comparison"
        ],
        "platforms": [
            "LeetCode"
        ],
        "level": "Easy",
        "link": "https://leetcode.com/problems/richest-customer-wealth/"
    },
    {
        "name": "Way Too Long Words",
        "tags": [
            "strings",
            "implementation"
        ],
        "platforms": [
            "Codeforces"
        ],
        "level": "Easy",
        "link": "https://codeforces.com/problemset/problem/71/A"
    },
    {
        "name": "Concatenation of Array",
        "tags": [
            "array",
            "concatenation",
            "list manipulation",
            "element repetition"
        ],
        "platforms": [
            "LeetCode"
        ],
        "level": "Easy",
        "link": "https://leetcode.com/problems/concatenation-of-array/"
    },
    {
        "name": "How Many Numbers Are Smaller Than the Current Number",
        "tags": [
            "array",
            "sorting",
            "counting",
            "element comparison"
        ],
        "platforms": [
            "LeetCode"
        ],
        "level": "Easy",
        "link": "https://leetcode.com/problems/how-many-numbers-are-smaller-than-the-current-number/"
    },
    {
        "name": "Find the Duplicate Number",
        "tags": [
            "array",
            "two pointers",
            "binary search",
            "duplicate"
        ],
        "platforms": [
            "LeetCode"
        ],
        "level": "Medium",
        "link": "https://leetcode.com/problems/find-the-duplicate-number/"
    },
    {
        "name": "Angled Flip",
        "tags": [
            "data structure",
            "algorithm"
        ],
        "platforms": [
            "Codechef"
        ],
        "level": "Medium",
        "link": "https://www.codechef.com/problems/AFLIP"
    },
    {
        "name": "Valid Parentheses",
        "tags": [
            "string",
            "stack",
            "parentheses",
            "validity checking"
        ],
        "platforms": [
            "LeetCode"
        ],
        "level": "Medium",
        "link": "https://leetcode.com/problems/valid-parentheses/"
    },
    {
        "name": "Letter Combinations of a Phone Number",
        "tags": [
            "string",
            "backtracking",
            "recursion",
            "combinations"
        ],
        "platforms": [
            "LeetCode"
        ],
        "level": "Medium",
        "link": "https://leetcode.com/problems/letter-combinations-of-a-phone-number/"
    },
    {
        "name": "Parity Again",
        "tags": [
            "math",
            "bit manipulation",
            "algorithm"
        ],
        "platforms": [
            "Codechef"
        ],
        "level": "Medium",
        "link": "https://www.codechef.com/problems/PRTAGN"
    },
    {
        "name": "One Dimensional Game of Life",
        "tags": [
            "math",
            "bit manipulation",
            "constructive"
        ],
        "platforms": [
            "Codechef"
        ],
        "level": "Medium",
        "link": "https://www.codechef.com/problems/LIFE"
    },
    {
        "name": "Marbles",
        "tags": [
            "dp"
        ],
        "platforms": [
            "LightOJ"
        ],
        "level": "Medium",
        "link": "https://lightoj.com/problem/marbles"
    },
    {
        "name": "Palindrome Linked List",
        "tags": [
            "linked list",
            "two pointers",
            "palindrome"
        ],
        "platforms": [
            "LeetCode"
        ],
        "level": "Medium",
        "link": "https://leetcode.com/problems/palindrome-linked-list/"
    },
    {
        "name": "Get The Containers",
        "tags": [
            "greedy"
        ],
        "platforms": [
            "LightOJ"
        ],
        "level": "Medium",
        "link": "https://lightoj.com/problem/get-the-containers"
    },
    {
        "name": "Bitwise Blend",
        "tags": [
            "constructive",
            "adhoc",
            "bruteforce",
            "algorithm"
        ],
        "platforms": [
            "Codechef"
        ],
        "level": "Medium",
        "link": "https://www.codechef.com/problems/BITBLEND"
    },
    {
        "name": "Minimum Path Sum",
        "tags": [
            "array",
            "dp",
            "grid",
            "path finding"
        ],
        "platforms": [
            "LeetCode"
        ],
        "level": "Medium",
        "link": "https://leetcode.com/problems/minimum-path-sum/"
    },
    {
        "name": "Lining Up",
        "tags": [
            "math",
            "permutations"
        ],
        "platforms": [
            "AtCoder"
        ],
        "level": "Medium",
        "link": "https://atcoder.jp/contests/abc142/tasks/abc142_d"
    },
    {
        "name": "Mex Array",
        "tags": [
            "data structure",
            "greedy",
            "algorithm"
        ],
        "platforms": [
            "Codechef"
        ],
        "level": "Medium",
        "link": "https://www.codechef.com/problems/MEX_ARRAY"
    },
    {
        "name": "The One with All the Candy",
        "tags": [
            "data structure",
            "algorithm"
        ],
        "platforms": [
            "Codechef"
        ],
        "level": "Medium",
        "link": "https://www.codechef.com/problems/S07E09"
    },
    {
        "name": "A Home for Chef",
        "tags": [
            "math",
            "algorithm"
        ],
        "platforms": [
            "Codechef"
        ],
        "level": "Medium",
        "link": "https://www.codechef.com/problems/CHEFHOME"
    },
    {
        "name": "Largest Y",
        "tags": [
            "math",
            "algorithm",
            "bit manipulation"
        ],
        "platforms": [
            "Codechef"
        ],
        "level": "Medium",
        "link": "https://www.codechef.com/problems/LARGESTY"
    },
    {
        "name": "Container With Most Water",
        "tags": [
            "array",
            "two pointers",
            "greedy",
            "water container"
        ],
        "platforms": [
            "LeetCode"
        ],
        "level": "Medium",
        "link": "https://leetcode.com/problems/container-with-most-water/"
    },
    {
        "name": "Subsets",
        "tags": [
            "array",
            "backtracking",
            "bit manipulation",
            "subsets"
        ],
        "platforms": [
            "LeetCode"
        ],
        "level": "Medium",
        "link": "https://leetcode.com/problems/subsets/"
    },
    {
        "name": "Agent 47",
        "tags": [
            "dp"
        ],
        "platforms": [
            "LightOJ"
        ],
        "level": "Medium",
        "link": "https://lightoj.com/problem/agent-47"
    },
    {
        "name": "Little Elephant and Alcohol",
        "tags": [
            "math",
            "bitmask"
        ],
        "platforms": [
            "Codechef"
        ],
        "level": "Medium",
        "link": "https://www.codechef.com/problems/LEALCO"
    },
    {
        "name": "Traveling Plan",
        "tags": [
            "graph",
            "shortest path"
        ],
        "platforms": [
            "AtCoder"
        ],
        "level": "Medium",
        "link": "https://atcoder.jp/contests/abc183/tasks/abc183_d"
    },
    {
        "name": "Valid Parentheses",
        "tags": [
            "string",
            "stack",
            "parentheses",
            "validity checking"
        ],
        "platforms": [
            "LeetCode"
        ],
        "level": "Medium",
        "link": "https://leetcode.com/problems/valid-parentheses/"
    },
    {
        "name": "Search a 2D Matrix",
        "tags": [
            "array",
            "binary search",
            "matrix",
            "searching"
        ],
        "platforms": [
            "LeetCode"
        ],
        "level": "Medium",
        "link": "https://leetcode.com/problems/search-a-2d-matrix/"
    },
    {
        "name": "Go Round",
        "tags": [
            "data structure",
            "adhoc",
            "algorithm",
            "constructive"
        ],
        "platforms": [
            "Codechef"
        ],
        "level": "Medium",
        "link": "https://www.codechef.com/problems/RNDRND"
    },
    {
        "name": "Maximise the bridges",
        "tags": [
            "constructive",
            "graph",
            "algorithm"
        ],
        "platforms": [
            "Codechef"
        ],
        "level": "Medium",
        "link": "https://www.codechef.com/problems/MAXBRIDGE"
    },
    {
        "name": "Jump Game III",
        "tags": [
            "array",
            "graph",
            "depth-first search",
            "breadth-first search"
        ],
        "platforms": [
            "LeetCode"
        ],
        "level": "Medium",
        "link": "https://leetcode.com/problems/jump-game-iii/"
    },
    {
        "name": "Minimum Window Substring",
        "tags": [
            "string",
            "two pointers",
            "sliding window",
            "substring"
        ],
        "platforms": [
            "LeetCode"
        ],
        "level": "Hard",
        "link": "https://leetcode.com/problems/minimum-window-substring/"
    },
    {
        "name": "Sabotaging Contest",
        "tags": [
            "data structure"
        ],
        "platforms": [
            "LightOJ"
        ],
        "level": "Hard",
        "link": "https://lightoj.com/problem/sabotaging-contest"
    },
    {
        "name": "Tree House",
        "tags": [
            "graph",
            "math",
            "data structure"
        ],
        "platforms": [
            "Codechef"
        ],
        "level": "Hard",
        "link": "https://www.codechef.com/problems/THOUSES"
    },
    {
        "name": "Circuit Board",
        "tags": [
            "binary search",
            "geometry"
        ],
        "platforms": [
            "AtCoder"
        ],
        "level": "Hard",
        "link": "https://atcoder.jp/contests/abc112/tasks/abc112_d"
    },
    {
        "name": "Minimum Window Substring",
        "tags": [
            "string",
            "two pointers",
            "sliding window",
            "substring"
        ],
        "platforms": [
            "LeetCode"
        ],
        "level": "Hard",
        "link": "https://leetcode.com/problems/minimum-window-substring/"
    },
    {
        "name": "Prime Factor Division",
        "tags": [
            "math",
            "number theory"
        ],
        "platforms": [
            "Codechef"
        ],
        "level": "Hard",
        "link": "https://www.codechef.com/problems/PRIMEFACDIV"
    },
    {
        "name": "Trapping Rain Water",
        "tags": [
            "Array",
            "Two Pointers",
            "Stack"
        ],
        "platforms": [
            "LeetCode"
        ],
        "level": "Hard",
        "link": "https://leetcode.com/problems/trapping-rain-water/"
    },
    {
        "name": "Little Elephant and Balloons",
        "tags": [
            "combinatorics",
            "dp",
            "math",
            "algorithm"
        ],
        "platforms": [
            "Codechef"
        ],
        "level": "Hard",
        "link": "https://www.codechef.com/problems/LEBALONS"
    },
    {
        "name": "Bytelandian Shoppers",
        "tags": [
            "combinatorics",
            "math"
        ],
        "platforms": [
            "Codechef"
        ],
        "level": "Hard",
        "link": "https://www.codechef.com/problems/BYTESHOP"
    },
    {
        "name": "Cutting Plants",
        "tags": [
            "data structure",
            "algorithm"
        ],
        "platforms": [
            "Codechef"
        ],
        "level": "Hard",
        "link": "https://www.codechef.com/problems/CUTPLANT"
    },
    {
        "name": "First Missing Positive",
        "tags": [
            "array",
            "hash table",
            "positive numbers",
            "missing"
        ],
        "platforms": [
            "LeetCode"
        ],
        "level": "Hard",
        "link": "https://leetcode.com/problems/first-missing-positive/"
    },
    {
        "name": "Median of Two Sorted Arrays",
        "tags": [
            "array",
            "binary search",
            "divide and conquer",
            "median"
        ],
        "platforms": [
            "LeetCode"
        ],
        "level": "Hard",
        "link": "https://leetcode.com/problems/median-of-two-sorted-arrays/"
    },
    {
        "name": "First Missing Positive",
        "tags": [
            "array",
            "hash table",
            "positive numbers",
            "missing"
        ],
        "platforms": [
            "LeetCode"
        ],
        "level": "Hard",
        "link": "https://leetcode.com/problems/first-missing-positive/"
    },
    {
        "name": "Maximum Factors Problem",
        "tags": [
            "greedy",
            "math"
        ],
        "platforms": [
            "Codechef"
        ],
        "level": "Hard",
        "link": "https://www.codechef.com/problems/MXFACS"
    },
    {
        "name": "Word Break II",
        "tags": [
            "string",
            "dp",
            "backtracking",
            "word break"
        ],
        "platforms": [
            "LeetCode"
        ],
        "level": "Hard",
        "link": "https://leetcode.com/problems/word-break-ii/"
    },
    {
        "name": "Largest Rectangle in Histogram",
        "tags": [
            "array",
            "stack",
            "monotonic stack",
            "histogram"
        ],
        "platforms": [
            "LeetCode"
        ],
        "level": "Hard",
        "link": "https://leetcode.com/problems/largest-rectangle-in-histogram/"
    },
    {
        "name": "Se7en",
        "tags": [
            "dp"
        ],
        "platforms": [
            "Codechef"
        ],
        "level": "Hard",
        "link": "https://www.codechef.com/problems/F4"
    },
    {
        "name": "Lunar New Year and a Wander",
        "tags": [
            "graph",
            "dfs"
        ],
        "platforms": [
            "AtCoder"
        ],
        "level": "Hard",
        "link": "https://atcoder.jp/contests/abc151/tasks/abc151_f"
    },
    {
        "name": "Chefina and Ranges",
        "tags": [
            "greedy",
            "data structure",
            "algorithm"
        ],
        "platforms": [
            "Codechef"
        ],
        "level": "Hard",
        "link": "https://www.codechef.com/problems/CHFRAN"
    },
    {
        "name": "N-Queens II",
        "tags": [
            "backtracking",
            "recursion",
            "queens"
        ],
        "platforms": [
            "LeetCode"
        ],
        "level": "Hard",
        "link": "https://leetcode.com/problems/n-queens-ii/"
    }
]