[
    {
        "name": "Power of Three",
        "tags": [
            "math",
            "number properties",
            "exponentiation",
            "divisibility"
        ],
        "platforms": [
            "LeetCode"
        ],
        "level": "Easy",
        "link": "https://leetcode.com/problems/power-of-three/"
    },
    {
        "name": "Number of Good Pairs",
        "tags": [
            "array",
            "hash table",
            "counting pairs",
            "combinatorics"
        ],
        "platforms": [
            "LeetCode"
        ],
        "level": "Easy",
        "link": "https://leetcode.com/problems/number-of-good-pairs/"
    },
    {
        "name": "Majority Element",
        "tags": [
            "array",
            "hash table",
            "voting algorithm",
            "majority detection"
        ],
        "platforms": [
            "LeetCode"
        ],
        "level": "Easy",
        "link": "https://leetcode.com/problems/majority-element/"
    },
    {
        "name": "Valid Parentheses",
        "tags": [
            "string",
            "stack"
        ],
        "platforms": [
            "LeetCode",
            "HackerRank"
        ],
        "level": "Easy",
        "link": "https://leetcode.com/problems/valid-parentheses/"
    },
    {
        "name": "Valid Anagram",
        "tags": [
            "string",
            "hash table",
            "algorithm"
        ],
        "platforms": [
            "LeetCode"
        ],
        "level": "Easy",
        "link": "https://leetcode.com/problems/valid-anagram/"
    },
    {
        "name": "Implement strStr()",
        "tags": [
            "Two Pointers",
            "String"
        ],
        "platforms": [
            "LeetCode"
        ],
        "level": "Easy",
        "link": "https://leetcode.com/problems/implement-strstr/"
    },
    {
        "name": "Remove Outermost Parentheses",
        "tags": [
            "string",
            "stack",
            "parentheses manipulation",
            "substring extraction"
        ],
        "platforms": [
            "LeetCode"
        ],
        "level": "Easy",
        "link": "https://leetcode.com/problems/remove-outermost-parentheses/"
    },
    {
        "name": "Valid Sudoku",
        "tags": [
            "array",
            "hash table",
            "matrix manipulation",
            "sudoku rules"
        ],
        "platforms": [
            "LeetCode"
        ],
        "level": "Easy",
        "link": "https://leetcode.com/problems/valid-sudoku/"
    },
    {
        "name": "Happy Number",
        "tags": [
            "math",
            "hash table"
        ],
        "platforms": [
            "LeetCode"
        ],
        "level": "Easy",
        "link": "https://leetcode.com/problems/happy-number/"
    },
    {
        "name": "Rotate Image",
        "tags": [
            "array",
            "matrix",
            "rotation",
            "transposition"
        ],
        "platforms": [
            "LeetCode"
        ],
        "level": "Medium",
        "link": "https://leetcode.com/problems/rotate-image/"
    },
    {
        "name": "Candidates of No Shortest Paths",
        "tags": [
            "graph",
            "dfs",
            "bfs"
        ],
        "platforms": [
            "AtCoder"
        ],
        "level": "Medium",
        "link": "https://atcoder.jp/contests/abc070/tasks/abc070_c"
    },
    {
        "name": "Monkeys On Twin Tower",
        "tags": [
            "dp"
        ],
        "platforms": [
            "LightOJ"
        ],
        "level": "Medium",
        "link": "https://lightoj.com/problem/monkeys-on-twin-tower"
    },
    {
        "name": "Consecutive Sum",
        "tags": [
            "data structure"
        ],
        "platforms": [
            "LightOJ"
        ],
        "level": "Medium",
        "link": "https://lightoj.com/problem/consecutive-sum"
    },
    {
        "name": "Bamboo Partition",
        "tags": [
            "binary search",
            "greedy"
        ],
        "platforms": [
            "Codeforces"
        ],
        "level": "Medium",
        "link": "https://codeforces.com/problemset/problem/830/B"
    },
    {
        "name": "A Gift From The Setter",
        "tags": [
            "greedy"
        ],
        "platforms": [
            "LightOJ"
        ],
        "level": "Medium",
        "link": "https://lightoj.com/problem/a-gift-from-the-setter"
    },
    {
        "name": "Old Sorting",
        "tags": [
            "greedy"
        ],
        "platforms": [
            "LightOJ"
        ],
        "level": "Medium",
        "link": "https://lightoj.com/problem/old-sorting"
    },
    {
        "name": "One Way Roads",
        "tags": [
            "graph"
        ],
        "platforms": [
            "LightOJ"
        ],
        "level": "Medium",
        "link": "https://lightoj.com/problem/one-way-roads"
    },
    {
        "name": "Fast Bit Calculations",
        "tags": [
            "dp"
        ],
        "platforms": [
            "LightOJ"
        ],
        "level": "Medium",
        "link": "https://lightoj.com/problem/fast-bit-calculations"
    },
    {
        "name": "Add Two Numbers II",
        "tags": [
            "linked list",
            "math",
            "addition",
            "reverse"
        ],
        "platforms": [
            "LeetCode"
        ],
        "level": "Medium",
        "link": "https://leetcode.com/problems/add-two-numbers-ii/"
    },
    {
        "name": "Helping Cicada",
        "tags": [
            "math"
        ],
        "platforms": [
            "LightOJ"
        ],
        "level": "Medium",
        "link": "https://lightoj.com/problem/helping-cicada"
    },
    {
        "name": "Valid Parentheses",
        "tags": [
            "string",
            "stack",
            "parentheses",
            "validity checking"
        ],
        "platforms": [
            "LeetCode"
        ],
        "level": "Medium",
        "link": "https://leetcode.com/problems/valid-parentheses/"
    },
    {
        "name": "Jump Game II",
        "tags": [
            "array",
            "greedy",
            "dp",
            "jump game"
        ],
        "platforms": [
            "LeetCode"
        ],
        "level": "Medium",
        "link": "https://leetcode.com/problems/jump-game-ii/"
    },
    {
        "name": "Remove Nth Node From End of List",
        "tags": [
            "linked list",
            "two pointers",
            "fast and slow pointers",
            "list manipulation"
        ],
        "platforms": [
            "LeetCode"
        ],
        "level": "Medium",
        "link": "https://leetcode.com/problems/remove-nth-node-from-end-of-list/"
    },
    {
        "name": "Aladdin and the Return Journey",
        "tags": [
            "data structure"
        ],
        "platforms": [
            "LightOJ"
        ],
        "level": "Medium",
        "link": "https://lightoj.com/problem/aladdin-and-the-return-journe"
    },
    {
        "name": "The Hungry Bear",
        "tags": [
            "dp",
            "algorithm"
        ],
        "platforms": [
            "Codechef"
        ],
        "level": "Medium",
        "link": "https://www.codechef.com/problems/HBEAR"
    },
    {
        "name": "Subarray Sum Equals K",
        "tags": [
            "Array",
            "Hash Table"
        ],
        "platforms": [
            "LeetCode"
        ],
        "level": "Medium",
        "link": "https://leetcode.com/problems/subarray-sum-equals-k/"
    },
    {
        "name": "Subtract 12 Operation",
        "tags": [
            "dp",
            "greedy",
            "algorithm"
        ],
        "platforms": [
            "Codechef"
        ],
        "level": "Medium",
        "link": "https://www.codechef.com/problems/SUB12OP"
    },
    {
        "name": "Lcs Revisited",
        "tags": [
            "dp"
        ],
        "platforms": [
            "LightOJ"
        ],
        "level": "Medium",
        "link": "https://lightoj.com/problem/lcs-revisited"
    },
    {
        "name": "Histogram",
        "tags": [
            "data structure"
        ],
        "platforms": [
            "LightOJ"
        ],
        "level": "Medium",
        "link": "https://lightoj.com/problem/histogram"
    },
    {
        "name": "Guddu and his Mother",
        "tags": [
            "math",
            "bit manipulation"
        ],
        "platforms": [
            "Codechef"
        ],
        "level": "Medium",
        "link": "https://www.codechef.com/problems/KS1"
    },
    {
        "name": "Critical Links",
        "tags": [
            "graph"
        ],
        "platforms": [
            "LightOJ"
        ],
        "level": "Medium",
        "link": "https://lightoj.com/problem/critical-links"
    },
    {
        "name": "Physics Class",
        "tags": [
            "data structure"
        ],
        "platforms": [
            "Codechef"
        ],
        "level": "Hard",
        "link": "https://www.codechef.com/problems/PHYSICS"
    },
    {
        "name": "Mexy Array",
        "tags": [
            "adhoc",
            "algorithm",
            "constructive"
        ],
        "platforms": [
            "Codechef"
        ],
        "level": "Hard",
        "link": "https://www.codechef.com/problems/MEXYARR"
    },
    {
        "name": "Magic Board",
        "tags": [
            "data structure"
        ],
        "platforms": [
            "Codechef"
        ],
        "level": "Hard",
        "link": "https://www.codechef.com/problems/MBOARD"
    },
    {
        "name": "First Missing Positive",
        "tags": [
            "array",
            "hash table",
            "positive numbers",
            "missing"
        ],
        "platforms": [
            "LeetCode"
        ],
        "level": "Hard",
        "link": "https://leetcode.com/problems/first-missing-positive/"
    },
    {
        "name": "Chef And Easy Xor Queries",
        "tags": [
            "bit manipulation",
            "math"
        ],
        "platforms": [
            "Codechef"
        ],
        "level": "Hard",
        "link": "https://www.codechef.com/problems/CHEFEXQ"
    },
    {
        "name": "Blind Escape",
        "tags": [
            "data structure"
        ],
        "platforms": [
            "LightOJ"
        ],
        "level": "Hard",
        "link": "https://lightoj.com/problem/blind-escape"
    },
    {
        "name": "Bytelandian Shoppers",
        "tags": [
            "combinatorics",
            "math"
        ],
        "platforms": [
            "Codechef"
        ],
        "level": "Hard",
        "link": "https://www.codechef.com/problems/BYTESHOP"
    },
    {
        "name": "Longest Valid Parentheses",
        "tags": [
            "string",
            "stack",
            "dp",
            "parentheses"
        ],
        "platforms": [
            "LeetCode"
        ],
        "level": "Hard",
        "link": "https://leetcode.com/problems/longest-valid-parentheses/"
    },
    {
        "name": "Los Pollos Hermanos",
        "tags": [
            "math",
            "combinatorics"
        ],
        "platforms": [
            "Codechef"
        ],
        "level": "Hard",
        "link": "https://www.codechef.com/problems/RRUN"
    },
    {
        "name": "Substring with Concatenation of All Words",
        "tags": [
            "string",
            "hash table",
            "substring",
            "concatenation"
        ],
        "platforms": [
            "LeetCode"
        ],
        "level": "Hard",
        "link": "https://leetcode.com/problems/substring-with-concatenation-of-all-words/"
    },
    {
        "name": "Roads in Chefland",
        "tags": [
            "math",
            "adhoc",
            "constructive",
            "bit manipulation"
        ],
        "platforms": [
            "Codechef"
        ],
        "level": "Hard",
        "link": "https://www.codechef.com/problems/CROADS"
    },
    {
        "name": "Hard 20",
        "tags": [
            "array",
            "backtracking",
            "hard"
        ],
        "platforms": [
            "LeetCode"
        ],
        "level": "Hard",
        "link": "https://leetcode.com/problems/hard-20/"
    },
    {
        "name": "Minimum Window Substring",
        "tags": [
            "string",
            "two pointers",
            "sliding window",
            "substring"
        ],
        "platforms": [
            "LeetCode"
        ],
        "level": "Hard",
        "link": "https://leetcode.com/problems/minimum-window-substring/"
    },
    {
        "name": "First Missing Positive",
        "tags": [
            "array",
            "hash table",
            "positive numbers",
            "missing"
        ],
        "platforms": [
            "LeetCode"
        ],
        "level": "Hard",
        "link": "https://leetcode.com/problems/first-missing-positive/"
    },
    {
        "name": "Software Company",
        "tags": [
            "dp"
        ],
        "platforms": [
            "LightOJ"
        ],
        "level": "Hard",
        "link": "https://lightoj.com/problem/software-company"
    },
    {
        "name": "N-Queens II",
        "tags": [
            "backtracking",
            "recursion",
            "queens"
        ],
        "platforms": [
            "LeetCode"
        ],
        "level": "Hard",
        "link": "https://leetcode.com/problems/n-queens-ii/"
    },
    {
        "name": "Minimum Window Substring",
        "tags": [
            "string",
            "hash table",
            "two pointers",
            "substring"
        ],
        "platforms": [
            "LeetCode"
        ],
        "level": "Hard",
        "link": "https://leetcode.com/problems/minimum-window-substring/"
    },
    {
        "name": "Minimum Window Substring",
        "tags": [
            "string",
            "two pointers",
            "sliding window",
            "substring"
        ],
        "platforms": [
            "LeetCode"
        ],
        "level": "Hard",
        "link": "https://leetcode.com/problems/minimum-window-substring/"
    },
    {
        "name": "Regular Expression Matching",
        "tags": [
            "String",
            "dp",
            "Backtracking"
        ],
        "platforms": [
            "LeetCode"
        ],
        "level": "Hard",
        "link": "https://leetcode.com/problems/regular-expression-matching/"
    },
    {
        "name": "Trapping Rain Water",
        "tags": [
            "array",
            "two pointers",
            "stack",
            "water trapping"
        ],
        "platforms": [
            "LeetCode"
        ],
        "level": "Hard",
        "link": "https://leetcode.com/problems/trapping-rain-water/"
    },
    {
        "name": "Sereja and Salesman",
        "tags": [
            "dp",
            "math"
        ],
        "platforms": [
            "Codechef"
        ],
        "level": "Hard",
        "link": "https://www.codechef.com/problems/SEAKAM"
    },
    {
        "name": "Distinct Subsequences",
        "tags": [
            "string",
            "dp",
            "subsequence",
            "distinct"
        ],
        "platforms": [
            "LeetCode"
        ],
        "level": "Hard",
        "link": "https://leetcode.com/problems/distinct-subsequences/"
    },
    {
        "name": "Expression Add Operators",
        "tags": [
            "string",
            "backtracking",
            "dfs",
            "expression"
        ],
        "platforms": [
            "LeetCode"
        ],
        "level": "Hard",
        "link": "https://leetcode.com/problems/expression-add-operators/"
    },
    {
        "name": "Points in Rectangle",
        "tags": [
            "data structure"
        ],
        "platforms": [
            "LightOJ"
        ],
        "level": "Hard",
        "link": "https://lightoj.com/problem/points-in-rectangle-ii"
    },
    {
        "name": "Little Elephant and Bubble Sort",
        "tags": [
            "data structure",
            "graph",
            "math",
            "probability"
        ],
        "platforms": [
            "Codechef"
        ],
        "level": "Hard",
        "link": "https://www.codechef.com/problems/LEBOBBLE"
    },
    {
        "name": "Useful Number",
        "tags": [
            "math",
            "number theory"
        ],
        "platforms": [
            "Codechef"
        ],
        "level": "Hard",
        "link": "https://www.codechef.com/problems/USF"
    },
    {
        "name": "N-Queens II",
        "tags": [
            "backtracking",
            "recursion",
            "queens"
        ],
        "platforms": [
            "LeetCode"
        ],
        "level": "Hard",
        "link": "https://leetcode.com/problems/n-queens-ii/"
    }
]