[
    {
        "name": "Reverse Words in a String",
        "tags": [
            "string",
            "string manipulation",
            "word reversal",
            "tokenization"
        ],
        "platforms": [
            "LeetCode"
        ],
        "level": "Easy",
        "link": "https://leetcode.com/problems/reverse-words-in-a-string/"
    },
    {
        "name": "Decompress Run-Length Encoded List",
        "tags": [
            "array",
            "compression",
            "list manipulation",
            "element expansion"
        ],
        "platforms": [
            "LeetCode"
        ],
        "level": "Easy",
        "link": "https://leetcode.com/problems/decompress-run-length-encoded-list/"
    },
    {
        "name": "Merge Two Sorted Lists",
        "tags": [
            "linked list",
            "sorting",
            "list manipulation",
            "pointers"
        ],
        "platforms": [
            "LeetCode"
        ],
        "level": "Easy",
        "link": "https://leetcode.com/problems/merge-two-sorted-lists/"
    },
    {
        "name": "Design Browser History",
        "tags": [
            "design",
            "linked list",
            "navigation history",
            "data structure"
        ],
        "platforms": [
            "LeetCode"
        ],
        "level": "Easy",
        "link": "https://leetcode.com/problems/design-browser-history/"
    },
    {
        "name": "Fizz Buzz",
        "tags": [
            "math",
            "conditional statements",
            "looping",
            "interview prep"
        ],
        "platforms": [
            "LeetCode"
        ],
        "level": "Easy",
        "link": "https://leetcode.com/problems/fizz-buzz/"
    },
    {
        "name": "Decompress Run-Length Encoded List",
        "tags": [
            "array",
            "compression",
            "list manipulation",
            "element expansion"
        ],
        "platforms": [
            "LeetCode"
        ],
        "level": "Easy",
        "link": "https://leetcode.com/problems/decompress-run-length-encoded-list/"
    },
    {
        "name": "Pascal's Triangle",
        "tags": [
            "array",
            "math",
            "pattern generation",
            "combinatorics"
        ],
        "platforms": [
            "LeetCode"
        ],
        "level": "Easy",
        "link": "https://leetcode.com/problems/pascals-triangle/"
    },
    {
        "name": "Valid Anagram",
        "tags": [
            "string",
            "hash table",
            "algorithm"
        ],
        "platforms": [
            "LeetCode"
        ],
        "level": "Easy",
        "link": "https://leetcode.com/problems/valid-anagram/"
    },
    {
        "name": "Merge Two Sorted Lists",
        "tags": [
            "linked list",
            "sorting",
            "algorithm"
        ],
        "platforms": [
            "LeetCode"
        ],
        "level": "Easy",
        "link": "https://leetcode.com/problems/merge-two-sorted-lists/"
    },
    {
        "name": "First Unique Character in a String",
        "tags": [
            "string",
            "hash table",
            "algorithm"
        ],
        "platforms": [
            "LeetCode"
        ],
        "level": "Easy",
        "link": "https://leetcode.com/problems/first-unique-character-in-a-string/"
    },
    {
        "name": "Valid Parentheses",
        "tags": [
            "String",
            "Stack"
        ],
        "platforms": [
            "LeetCode"
        ],
        "level": "Easy",
        "link": "https://leetcode.com/problems/valid-parentheses/"
    },
    {
        "name": "Richest Customer Wealth",
        "tags": [
            "array",
            "wealth calculation",
            "element sum",
            "richness comparison"
        ],
        "platforms": [
            "LeetCode"
        ],
        "level": "Easy",
        "link": "https://leetcode.com/problems/richest-customer-wealth/"
    },
    {
        "name": "Reverse Only Letters",
        "tags": [
            "string",
            "two pointers",
            "character manipulation",
            "letter reversal"
        ],
        "platforms": [
            "LeetCode"
        ],
        "level": "Easy",
        "link": "https://leetcode.com/problems/reverse-only-letters/"
    },
    {
        "name": "Sum of All Odd Length Subarrays",
        "tags": [
            "array",
            "subarray sum",
            "odd length subarrays",
            "combinatorics"
        ],
        "platforms": [
            "LeetCode"
        ],
        "level": "Easy",
        "link": "https://leetcode.com/problems/sum-of-all-odd-length-subarrays/"
    },
    {
        "name": "Find the Highest Altitude",
        "tags": [
            "array",
            "tracking",
            "altitude calculation",
            "element comparison"
        ],
        "platforms": [
            "LeetCode"
        ],
        "level": "Easy",
        "link": "https://leetcode.com/problems/find-the-highest-altitude/"
    },
    {
        "name": "Word Capitalization",
        "tags": [
            "strings",
            "implementation"
        ],
        "platforms": [
            "Codeforces"
        ],
        "level": "Easy",
        "link": "https://codeforces.com/problemset/problem/281/A"
    },
    {
        "name": "Count and Say",
        "tags": [
            "string",
            "pattern recognition",
            "sequence generation",
            "recursion"
        ],
        "platforms": [
            "LeetCode"
        ],
        "level": "Easy",
        "link": "https://leetcode.com/problems/count-and-say/"
    },
    {
        "name": "Longest Common Prefix",
        "tags": [
            "string",
            "prefix matching",
            "character comparison",
            "divide and conquer"
        ],
        "platforms": [
            "LeetCode"
        ],
        "level": "Easy",
        "link": "https://leetcode.com/problems/longest-common-prefix/"
    },
    {
        "name": "Remove Outermost Parentheses",
        "tags": [
            "string",
            "stack",
            "parentheses manipulation",
            "substring extraction"
        ],
        "platforms": [
            "LeetCode"
        ],
        "level": "Easy",
        "link": "https://leetcode.com/problems/remove-outermost-parentheses/"
    },
    {
        "name": "Maximum 69 Number",
        "tags": [
            "math",
            "number manipulation",
            "digit substitution",
            "number properties"
        ],
        "platforms": [
            "LeetCode"
        ],
        "level": "Easy",
        "link": "https://leetcode.com/problems/maximum-69-number/"
    },
    {
        "name": "Plus One",
        "tags": [
            "array",
            "math",
            "addition operation",
            "carry handling"
        ],
        "platforms": [
            "LeetCode"
        ],
        "level": "Easy",
        "link": "https://leetcode.com/problems/plus-one/"
    },
    {
        "name": "Curious Robin Hood",
        "tags": [
            "data structure"
        ],
        "platforms": [
            "LightOJ"
        ],
        "level": "Easy",
        "link": "https://lightoj.com/problem/curious-robin-hood"
    },
    {
        "name": "Merge Sorted Array",
        "tags": [
            "Array",
            "Two Pointers"
        ],
        "platforms": [
            "LeetCode"
        ],
        "level": "Easy",
        "link": "https://leetcode.com/problems/merge-sorted-array/"
    },
    {
        "name": "Valid Sudoku",
        "tags": [
            "array",
            "hash table",
            "matrix manipulation",
            "sudoku rules"
        ],
        "platforms": [
            "LeetCode"
        ],
        "level": "Easy",
        "link": "https://leetcode.com/problems/valid-sudoku/"
    },
    {
        "name": "Word Capitalization",
        "tags": [
            "strings",
            "implementation"
        ],
        "platforms": [
            "Codeforces"
        ],
        "level": "Easy",
        "link": "https://codeforces.com/problemset/problem/281/A"
    },
    {
        "name": "Reverse Integer",
        "tags": [
            "math"
        ],
        "platforms": [
            "LeetCode"
        ],
        "level": "Easy",
        "link": "https://leetcode.com/problems/reverse-integer/"
    },
    {
        "name": "Find All Anagrams in a String",
        "tags": [
            "string",
            "sliding window",
            "hash table",
            "anagram detection"
        ],
        "platforms": [
            "LeetCode"
        ],
        "level": "Easy",
        "link": "https://leetcode.com/problems/find-all-anagrams-in-a-string/"
    },
    {
        "name": "Palindrome Partitioning",
        "tags": [
            "backtracking",
            "string",
            "partitioning",
            "palindrome"
        ],
        "platforms": [
            "LeetCode"
        ],
        "level": "Medium",
        "link": "https://leetcode.com/problems/palindrome-partitioning/"
    },
    {
        "name": "Matrix Game",
        "tags": [
            "games"
        ],
        "platforms": [
            "LightOJ"
        ],
        "level": "Medium",
        "link": "https://lightoj.com/problem/matrix-game"
    },
    {
        "name": "Chef and Modulo Game",
        "tags": [
            "math",
            "combinatorics"
        ],
        "platforms": [
            "Codechef"
        ],
        "level": "Medium",
        "link": "https://www.codechef.com/problems/MGAME"
    },
    {
        "name": "Get The Containers",
        "tags": [
            "greedy"
        ],
        "platforms": [
            "LightOJ"
        ],
        "level": "Medium",
        "link": "https://lightoj.com/problem/get-the-containers"
    },
    {
        "name": "Valid String",
        "tags": [
            "data structure"
        ],
        "platforms": [
            "Codechef"
        ],
        "level": "Hard",
        "link": "https://www.codechef.com/problems/VSTRING"
    },
    {
        "name": "Minimum Window Substring",
        "tags": [
            "string",
            "two pointers",
            "sliding window",
            "substring"
        ],
        "platforms": [
            "LeetCode"
        ],
        "level": "Hard",
        "link": "https://leetcode.com/problems/minimum-window-substring/"
    },
    {
        "name": "Word Break II",
        "tags": [
            "string",
            "dp",
            "backtracking",
            "word break"
        ],
        "platforms": [
            "LeetCode"
        ],
        "level": "Hard",
        "link": "https://leetcode.com/problems/word-break-ii/"
    },
    {
        "name": "Divide by Three, Multiply by Two",
        "tags": [
            "brute force",
            "dfs and similar",
            "greedy"
        ],
        "platforms": [
            "Codeforces"
        ],
        "level": "Hard",
        "link": "https://codeforces.com/problemset/problem/966/D"
    },
    {
        "name": "Greg and Array",
        "tags": [
            "data structure",
            "dp",
            "implementation"
        ],
        "platforms": [
            "Codeforces"
        ],
        "level": "Hard",
        "link": "https://codeforces.com/problemset/problem/295/A"
    },
    {
        "name": "First Missing Positive",
        "tags": [
            "array",
            "hash table",
            "positive numbers",
            "missing"
        ],
        "platforms": [
            "LeetCode"
        ],
        "level": "Hard",
        "link": "https://leetcode.com/problems/first-missing-positive/"
    },
    {
        "name": "The Magical Stone",
        "tags": [
            "combinatorics",
            "math"
        ],
        "platforms": [
            "Codechef"
        ],
        "level": "Hard",
        "link": "https://www.codechef.com/problems/MAGICSTONE"
    },
    {
        "name": "Substring with Concatenation of All Words",
        "tags": [
            "string",
            "hash table",
            "substring",
            "concatenation"
        ],
        "platforms": [
            "LeetCode"
        ],
        "level": "Hard",
        "link": "https://leetcode.com/problems/substring-with-concatenation-of-all-words/"
    },
    {
        "name": "Chef and Magical Steps",
        "tags": [
            "dp",
            "math",
            "algorithm"
        ],
        "platforms": [
            "Codechef"
        ],
        "level": "Hard",
        "link": "https://www.codechef.com/problems/CHEFMGX"
    },
    {
        "name": "Longest Valid Parentheses",
        "tags": [
            "string",
            "stack",
            "dp",
            "parentheses"
        ],
        "platforms": [
            "LeetCode"
        ],
        "level": "Hard",
        "link": "https://leetcode.com/problems/longest-valid-parentheses/"
    },
    {
        "name": "Longest Substring with At Most K Distinct Characters",
        "tags": [
            "string",
            "sliding window",
            "hash table",
            "distinct characters"
        ],
        "platforms": [
            "LeetCode"
        ],
        "level": "Hard",
        "link": "https://leetcode.com/problems/longest-substring-with-at-most-k-distinct-characters/"
    },
    {
        "name": "Little Elephant and Balloons",
        "tags": [
            "combinatorics",
            "dp",
            "math",
            "algorithm"
        ],
        "platforms": [
            "Codechef"
        ],
        "level": "Hard",
        "link": "https://www.codechef.com/problems/LEBALONS"
    },
    {
        "name": "Walk",
        "tags": [
            "graph",
            "dfs"
        ],
        "platforms": [
            "AtCoder"
        ],
        "level": "Hard",
        "link": "https://atcoder.jp/contests/abc088/tasks/abc088_d"
    },
    {
        "name": "Trapping Rain Water",
        "tags": [
            "Array",
            "Two Pointers",
            "Stack"
        ],
        "platforms": [
            "LeetCode"
        ],
        "level": "Hard",
        "link": "https://leetcode.com/problems/trapping-rain-water/"
    },
    {
        "name": "Gears",
        "tags": [
            "graph",
            "data structure"
        ],
        "platforms": [
            "Codechef"
        ],
        "level": "Hard",
        "link": "https://www.codechef.com/problems/GEARS"
    },
    {
        "name": "Regular Expression Matching",
        "tags": [
            "string",
            "dp",
            "backtracking",
            "regular expression"
        ],
        "platforms": [
            "LeetCode"
        ],
        "level": "Hard",
        "link": "https://leetcode.com/problems/regular-expression-matching/"
    },
    {
        "name": "ChefGame",
        "tags": [
            "data structure",
            "graph"
        ],
        "platforms": [
            "Codechef"
        ],
        "level": "Hard",
        "link": "https://www.codechef.com/problems/CHEFGAME"
    },
    {
        "name": "Polycarp and Hay",
        "tags": [
            "binary search",
            "greedy",
            "sortings"
        ],
        "platforms": [
            "Codeforces"
        ],
        "level": "Hard",
        "link": "https://codeforces.com/problemset/problem/1144/C"
    },
    {
        "name": "Minimum Window Substring",
        "tags": [
            "string",
            "two pointers",
            "sliding window",
            "substring"
        ],
        "platforms": [
            "LeetCode"
        ],
        "level": "Hard",
        "link": "https://leetcode.com/problems/minimum-window-substring/"
    },
    {
        "name": "Traffic jam",
        "tags": [
            "dp"
        ],
        "platforms": [
            "Codechef"
        ],
        "level": "Hard",
        "link": "https://www.codechef.com/problems/N5"
    },
    {
        "name": "Online Shopping",
        "tags": [
            "dp",
            "data structure",
            "math"
        ],
        "platforms": [
            "Codechef"
        ],
        "level": "Hard",
        "link": "https://www.codechef.com/problems/COUPON"
    }
]