[
    {
        "name": "Running Sum of 1d Array",
        "tags": [
            "array",
            "running sum",
            "cumulative sum",
            "element addition"
        ],
        "platforms": [
            "LeetCode"
        ],
        "level": "Easy",
        "link": "https://leetcode.com/problems/running-sum-of-1d-array/"
    },
    {
        "name": "Richest Customer Wealth",
        "tags": [
            "array",
            "wealth calculation",
            "element sum",
            "richness comparison"
        ],
        "platforms": [
            "LeetCode"
        ],
        "level": "Easy",
        "link": "https://leetcode.com/problems/richest-customer-wealth/"
    },
    {
        "name": "Roman to Integer",
        "tags": [
            "math",
            "String"
        ],
        "platforms": [
            "LeetCode"
        ],
        "level": "Easy",
        "link": "https://leetcode.com/problems/roman-to-integer/"
    },
    {
        "name": "Search a 2D Matrix",
        "tags": [
            "array",
            "binary search",
            "matrix",
            "searching"
        ],
        "platforms": [
            "LeetCode"
        ],
        "level": "Medium",
        "link": "https://leetcode.com/problems/search-a-2d-matrix/"
    },
    {
        "name": "Coin Change",
        "tags": [
            "array",
            "dp",
            "coin change",
            "combinations"
        ],
        "platforms": [
            "LeetCode"
        ],
        "level": "Medium",
        "link": "https://leetcode.com/problems/coin-change/"
    },
    {
        "name": "Scramble String",
        "tags": [
            "string",
            "dp",
            "recursion",
            "scramble"
        ],
        "platforms": [
            "LeetCode"
        ],
        "level": "Hard",
        "link": "https://leetcode.com/problems/scramble-string/"
    },
    {
        "name": "Regular Expression Matching",
        "tags": [
            "string",
            "dp",
            "backtracking",
            "regular expression"
        ],
        "platforms": [
            "LeetCode"
        ],
        "level": "Hard",
        "link": "https://leetcode.com/problems/regular-expression-matching/"
    },
    {
        "name": "Yalalovichik Numbers",
        "tags": [
            "math"
        ],
        "platforms": [
            "Codechef"
        ],
        "level": "Hard",
        "link": "https://www.codechef.com/problems/YVNUM"
    },
    {
        "name": "Sereja and Salesman",
        "tags": [
            "dp",
            "math"
        ],
        "platforms": [
            "Codechef"
        ],
        "level": "Hard",
        "link": "https://www.codechef.com/problems/SEAKAM"
    },
    {
        "name": "Median of Two Sorted Arrays",
        "tags": [
            "array",
            "binary search",
            "divide and conquer"
        ],
        "platforms": [
            "LeetCode"
        ],
        "level": "Hard",
        "link": "https://leetcode.com/problems/median-of-two-sorted-arrays/"
    },
    {
        "name": "Word Break II",
        "tags": [
            "string",
            "dp",
            "backtracking",
            "word break"
        ],
        "platforms": [
            "LeetCode"
        ],
        "level": "Hard",
        "link": "https://leetcode.com/problems/word-break-ii/"
    },
    {
        "name": "Palindrome Pairs",
        "tags": [
            "string",
            "hash table",
            "trie",
            "palindrome"
        ],
        "platforms": [
            "LeetCode"
        ],
        "level": "Hard",
        "link": "https://leetcode.com/problems/palindrome-pairs/"
    },
    {
        "name": "Maximum Subarray",
        "tags": [
            "array",
            "divide and conquer",
            "dp",
            "subarray"
        ],
        "platforms": [
            "LeetCode"
        ],
        "level": "Hard",
        "link": "https://leetcode.com/problems/maximum-subarray/"
    },
    {
        "name": "Diagonal Sum",
        "tags": [
            "greedy"
        ],
        "platforms": [
            "LightOJ"
        ],
        "level": "Hard",
        "link": "https://lightoj.com/problem/diagonal-sum"
    },
    {
        "name": "First Missing Positive",
        "tags": [
            "array",
            "hash table",
            "positive numbers",
            "missing"
        ],
        "platforms": [
            "LeetCode"
        ],
        "level": "Hard",
        "link": "https://leetcode.com/problems/first-missing-positive/"
    },
    {
        "name": "Chef and Gcd Queries",
        "tags": [
            "data structure",
            "math"
        ],
        "platforms": [
            "Codechef"
        ],
        "level": "Hard",
        "link": "https://www.codechef.com/problems/GCDCNT"
    },
    {
        "name": "Hard 20",
        "tags": [
            "array",
            "backtracking",
            "hard"
        ],
        "platforms": [
            "LeetCode"
        ],
        "level": "Hard",
        "link": "https://leetcode.com/problems/hard-20/"
    },
    {
        "name": "Gears",
        "tags": [
            "graph",
            "data structure"
        ],
        "platforms": [
            "Codechef"
        ],
        "level": "Hard",
        "link": "https://www.codechef.com/problems/GEARS"
    },
    {
        "name": "Grouping Friends",
        "tags": [
            "dp"
        ],
        "platforms": [
            "LightOJ"
        ],
        "level": "Hard",
        "link": "https://lightoj.com/problem/grouping-friends"
    },
    {
        "name": "First Missing Positive",
        "tags": [
            "array",
            "hash table",
            "positive numbers",
            "missing"
        ],
        "platforms": [
            "LeetCode"
        ],
        "level": "Hard",
        "link": "https://leetcode.com/problems/first-missing-positive/"
    },
    {
        "name": "Bytelandian Shoppers",
        "tags": [
            "combinatorics",
            "math"
        ],
        "platforms": [
            "Codechef"
        ],
        "level": "Hard",
        "link": "https://www.codechef.com/problems/BYTESHOP"
    },
    {
        "name": "Chef and Subarrays",
        "tags": [
            "data structure",
            "math"
        ],
        "platforms": [
            "Codechef"
        ],
        "level": "Hard",
        "link": "https://www.codechef.com/problems/CHEFARRB"
    },
    {
        "name": "Substring with Concatenation of All Words",
        "tags": [
            "string",
            "hash table",
            "substring",
            "concatenation"
        ],
        "platforms": [
            "LeetCode"
        ],
        "level": "Hard",
        "link": "https://leetcode.com/problems/substring-with-concatenation-of-all-words/"
    },
    {
        "name": "Skiing",
        "tags": [
            "greedy",
            "data structure",
            "graph",
            "sorting"
        ],
        "platforms": [
            "Codechef"
        ],
        "level": "Hard",
        "link": "https://www.codechef.com/problems/SKIING"
    },
    {
        "name": "Minimize swaps",
        "tags": [
            "dp",
            "adhoc",
            "constructive"
        ],
        "platforms": [
            "Codechef"
        ],
        "level": "Hard",
        "link": "https://www.codechef.com/problems/DIVBY3"
    },
    {
        "name": "Line Chart",
        "tags": [
            "data structure"
        ],
        "platforms": [
            "LightOJ"
        ],
        "level": "Hard",
        "link": "https://lightoj.com/problem/line-chart"
    },
    {
        "name": "Regular Expression Matching",
        "tags": [
            "string",
            "dp",
            "backtracking",
            "regular expression"
        ],
        "platforms": [
            "LeetCode"
        ],
        "level": "Hard",
        "link": "https://leetcode.com/problems/regular-expression-matching/"
    },
    {
        "name": "Median of Two Sorted Arrays",
        "tags": [
            "array",
            "binary search",
            "divide and conquer",
            "median"
        ],
        "platforms": [
            "LeetCode"
        ],
        "level": "Hard",
        "link": "https://leetcode.com/problems/median-of-two-sorted-arrays/"
    },
    {
        "name": "Substring with Concatenation of All Words",
        "tags": [
            "string",
            "hash table",
            "sliding window",
            "concatenation"
        ],
        "platforms": [
            "LeetCode"
        ],
        "level": "Hard",
        "link": "https://leetcode.com/problems/substring-with-concatenation-of-all-words/"
    },
    {
        "name": "Palindrome Pairs",
        "tags": [
            "string",
            "hash table",
            "trie",
            "palindrome"
        ],
        "platforms": [
            "LeetCode"
        ],
        "level": "Hard",
        "link": "https://leetcode.com/problems/palindrome-pairs/"
    },
    {
        "name": "Chef and Prime Queries",
        "tags": [
            "data structure",
            "math"
        ],
        "platforms": [
            "Codechef"
        ],
        "level": "Hard",
        "link": "https://www.codechef.com/problems/PRMQ"
    },
    {
        "name": "Chefina and Prefix Suffix Sums",
        "tags": [
            "math",
            "combinatorics"
        ],
        "platforms": [
            "Codechef"
        ],
        "level": "Hard",
        "link": "https://www.codechef.com/problems/CHEFPSA"
    },
    {
        "name": "Substring with Concatenation of All Words",
        "tags": [
            "string",
            "hash table",
            "substring",
            "concatenation"
        ],
        "platforms": [
            "LeetCode"
        ],
        "level": "Hard",
        "link": "https://leetcode.com/problems/substring-with-concatenation-of-all-words/"
    },
    {
        "name": "Regular Expression Matching",
        "tags": [
            "String",
            "dp",
            "Backtracking"
        ],
        "platforms": [
            "LeetCode"
        ],
        "level": "Hard",
        "link": "https://leetcode.com/problems/regular-expression-matching/"
    }
]