[
    {
        "name": "Intersection of Two Arrays II",
        "tags": [
            "hash table",
            "two pointers",
            "binary search"
        ],
        "platforms": [
            "LeetCode"
        ],
        "level": "Easy",
        "link": "https://leetcode.com/problems/intersection-of-two-arrays-ii/"
    },
    {
        "name": "Happy Number",
        "tags": [
            "math",
            "cycle detection",
            "number transformation",
            "mathematical properties"
        ],
        "platforms": [
            "LeetCode"
        ],
        "level": "Easy",
        "link": "https://leetcode.com/problems/happy-number/"
    },
    {
        "name": "Intersection of Two Arrays II",
        "tags": [
            "array",
            "hash table",
            "sorting",
            "intersection"
        ],
        "platforms": [
            "LeetCode"
        ],
        "level": "Easy",
        "link": "https://leetcode.com/problems/intersection-of-two-arrays-ii/"
    },
    {
        "name": "Palindrome Partitioning",
        "tags": [
            "backtracking",
            "string",
            "partitioning",
            "palindrome detection"
        ],
        "platforms": [
            "LeetCode"
        ],
        "level": "Easy",
        "link": "https://leetcode.com/problems/palindrome-partitioning/"
    },
    {
        "name": "Find Numbers with Even Number of Digits",
        "tags": [
            "array",
            "number manipulation",
            "digit counting",
            "integer properties"
        ],
        "platforms": [
            "LeetCode"
        ],
        "level": "Easy",
        "link": "https://leetcode.com/problems/find-numbers-with-even-number-of-digits/"
    },
    {
        "name": "Reverse Only Letters",
        "tags": [
            "string",
            "two pointers",
            "character manipulation",
            "letter reversal"
        ],
        "platforms": [
            "LeetCode"
        ],
        "level": "Easy",
        "link": "https://leetcode.com/problems/reverse-only-letters/"
    },
    {
        "name": "Maximum 69 Number",
        "tags": [
            "math",
            "number manipulation",
            "digit substitution",
            "number properties"
        ],
        "platforms": [
            "LeetCode"
        ],
        "level": "Easy",
        "link": "https://leetcode.com/problems/maximum-69-number/"
    },
    {
        "name": "Ant Network",
        "tags": [
            "graph"
        ],
        "platforms": [
            "LightOJ"
        ],
        "level": "Medium",
        "link": "https://lightoj.com/problem/ant-network"
    },
    {
        "name": "Min Max Roads",
        "tags": [
            "data structure"
        ],
        "platforms": [
            "LightOJ"
        ],
        "level": "Medium",
        "link": "https://lightoj.com/problem/min-max-roads"
    },
    {
        "name": "Equality Etiquette",
        "tags": [
            "math",
            "searching"
        ],
        "platforms": [
            "Codechef"
        ],
        "level": "Medium",
        "link": "https://www.codechef.com/problems/EQUAL2"
    },
    {
        "name": "Concert",
        "tags": [
            "greedy",
            "sortings"
        ],
        "platforms": [
            "Codeforces"
        ],
        "level": "Medium",
        "link": "https://codeforces.com/problemset/problem/664/A"
    },
    {
        "name": "Connecting Soldiers",
        "tags": [
            "math",
            "bitmask",
            "algorithm"
        ],
        "platforms": [
            "Codechef"
        ],
        "level": "Medium",
        "link": "https://www.codechef.com/problems/NOKIA"
    },
    {
        "name": "Manhattan Rectangle",
        "tags": [
            "math",
            "geometry"
        ],
        "platforms": [
            "Codechef"
        ],
        "level": "Medium",
        "link": "https://www.codechef.com/problems/MANRECT"
    },
    {
        "name": "Queue",
        "tags": [
            "data structure",
            "implementation"
        ],
        "platforms": [
            "Codeforces"
        ],
        "level": "Medium",
        "link": "https://codeforces.com/problemset/problem/545/D"
    },
    {
        "name": "Subarray Sum Equals K",
        "tags": [
            "Array",
            "Hash Table"
        ],
        "platforms": [
            "LeetCode"
        ],
        "level": "Medium",
        "link": "https://leetcode.com/problems/subarray-sum-equals-k/"
    },
    {
        "name": "Points in Rectangle",
        "tags": [
            "data structure"
        ],
        "platforms": [
            "LightOJ"
        ],
        "level": "Medium",
        "link": "https://lightoj.com/problem/points-in-rectangle"
    },
    {
        "name": "Number of Islands",
        "tags": [
            "depth-first search",
            "breadth-first search",
            "union-find",
            "graph",
            "island counting"
        ],
        "platforms": [
            "LeetCode"
        ],
        "level": "Medium",
        "link": "https://leetcode.com/problems/number-of-islands/"
    },
    {
        "name": "Search a 2D Matrix",
        "tags": [
            "array",
            "binary search",
            "matrix",
            "searching"
        ],
        "platforms": [
            "LeetCode"
        ],
        "level": "Medium",
        "link": "https://leetcode.com/problems/search-a-2d-matrix/"
    },
    {
        "name": "Combination Sum II",
        "tags": [
            "array",
            "backtracking",
            "recursion",
            "combination"
        ],
        "platforms": [
            "LeetCode"
        ],
        "level": "Medium",
        "link": "https://leetcode.com/problems/combination-sum-ii/"
    },
    {
        "name": "Maximal Square",
        "tags": [
            "array",
            "dp",
            "matrix",
            "square"
        ],
        "platforms": [
            "LeetCode"
        ],
        "level": "Medium",
        "link": "https://leetcode.com/problems/maximal-square/"
    },
    {
        "name": "Free Cash",
        "tags": [
            "implementation",
            "sortings"
        ],
        "platforms": [
            "Codeforces"
        ],
        "level": "Medium",
        "link": "https://codeforces.com/problemset/problem/237/A"
    },
    {
        "name": "Word Search",
        "tags": [
            "array",
            "backtracking",
            "matrix",
            "word search"
        ],
        "platforms": [
            "LeetCode"
        ],
        "level": "Medium",
        "link": "https://leetcode.com/problems/word-search/"
    },
    {
        "name": "Chef and Prime Queries",
        "tags": [
            "data structure",
            "math"
        ],
        "platforms": [
            "Codechef"
        ],
        "level": "Hard",
        "link": "https://www.codechef.com/problems/PRMQ"
    },
    {
        "name": "Substring with Concatenation of All Words",
        "tags": [
            "string",
            "hash table",
            "substring",
            "concatenation"
        ],
        "platforms": [
            "LeetCode"
        ],
        "level": "Hard",
        "link": "https://leetcode.com/problems/substring-with-concatenation-of-all-words/"
    },
    {
        "name": "Trapping Rain Water",
        "tags": [
            "Array",
            "Two Pointers",
            "Stack"
        ],
        "platforms": [
            "LeetCode"
        ],
        "level": "Hard",
        "link": "https://leetcode.com/problems/trapping-rain-water/"
    },
    {
        "name": "Infinite OR Game",
        "tags": [
            "greedy",
            "math",
            "bit manipulation"
        ],
        "platforms": [
            "Codechef"
        ],
        "level": "Hard",
        "link": "https://www.codechef.com/problems/LIKECS03"
    },
    {
        "name": "Median of Two Sorted Arrays",
        "tags": [
            "array",
            "binary search",
            "divide and conquer",
            "median"
        ],
        "platforms": [
            "LeetCode"
        ],
        "level": "Hard",
        "link": "https://leetcode.com/problems/median-of-two-sorted-arrays/"
    },
    {
        "name": "Minimum Window Substring",
        "tags": [
            "string",
            "two pointers",
            "sliding window",
            "substring"
        ],
        "platforms": [
            "LeetCode"
        ],
        "level": "Hard",
        "link": "https://leetcode.com/problems/minimum-window-substring/"
    }
]