[
    {
        "name": "Reverse Only Letters",
        "tags": [
            "string",
            "two pointers",
            "character manipulation",
            "letter reversal"
        ],
        "platforms": [
            "LeetCode"
        ],
        "level": "Easy",
        "link": "https://leetcode.com/problems/reverse-only-letters/"
    },
    {
        "name": "Palindrome Partitioning",
        "tags": [
            "backtracking",
            "string",
            "partitioning",
            "palindrome detection"
        ],
        "platforms": [
            "LeetCode"
        ],
        "level": "Easy",
        "link": "https://leetcode.com/problems/palindrome-partitioning/"
    },
    {
        "name": "Binary Search",
        "tags": [
            "binary search",
            "searching",
            "sorted array",
            "recursive approach"
        ],
        "platforms": [
            "LeetCode"
        ],
        "level": "Easy",
        "link": "https://leetcode.com/problems/binary-search/"
    },
    {
        "name": "Two Sum",
        "tags": [
            "arrays",
            "hash table"
        ],
        "platforms": [
            "LeetCode",
            "HackerRank"
        ],
        "level": "Easy",
        "link": "https://leetcode.com/problems/two-sum/"
    },
    {
        "name": "Reverse String",
        "tags": [
            "String"
        ],
        "platforms": [
            "LeetCode"
        ],
        "level": "Easy",
        "link": "https://leetcode.com/problems/reverse-string/"
    },
    {
        "name": "Count Primes",
        "tags": [
            "math",
            "prime numbers",
            "sieve of Eratosthenes",
            "number theory"
        ],
        "platforms": [
            "LeetCode"
        ],
        "level": "Easy",
        "link": "https://leetcode.com/problems/count-primes/"
    },
    {
        "name": "Two Sum",
        "tags": [
            "arrays",
            "hash table",
            "searching",
            "algorithm"
        ],
        "platforms": [
            "LeetCode",
            "HackerRank"
        ],
        "level": "Easy",
        "link": "https://leetcode.com/problems/two-sum/"
    },
    {
        "name": "Valid Anagram",
        "tags": [
            "hash table",
            "sorting",
            "character frequency",
            "anagram detection"
        ],
        "platforms": [
            "LeetCode"
        ],
        "level": "Easy",
        "link": "https://leetcode.com/problems/valid-anagram/"
    },
    {
        "name": "Shuffle the Array",
        "tags": [
            "array",
            "shuffling",
            "element rearrangement",
            "randomization"
        ],
        "platforms": [
            "LeetCode"
        ],
        "level": "Easy",
        "link": "https://leetcode.com/problems/shuffle-the-array/"
    },
    {
        "name": "Maximum Population Year",
        "tags": [
            "array",
            "population tracking",
            "year calculation",
            "element comparison"
        ],
        "platforms": [
            "LeetCode"
        ],
        "level": "Easy",
        "link": "https://leetcode.com/problems/maximum-population-year/"
    },
    {
        "name": "Check If Two String Arrays are Equivalent",
        "tags": [
            "string",
            "array",
            "string comparison",
            "concatenation"
        ],
        "platforms": [
            "LeetCode"
        ],
        "level": "Easy",
        "link": "https://leetcode.com/problems/check-if-two-string-arrays-are-equivalent/"
    },
    {
        "name": "Puzzles",
        "tags": [
            "greedy",
            "sortings"
        ],
        "platforms": [
            "Codeforces"
        ],
        "level": "Easy",
        "link": "https://codeforces.com/problemset/problem/337/A"
    },
    {
        "name": "Sum of All Odd Length Subarrays",
        "tags": [
            "array",
            "subarray sum",
            "odd length subarrays",
            "combinatorics"
        ],
        "platforms": [
            "LeetCode"
        ],
        "level": "Easy",
        "link": "https://leetcode.com/problems/sum-of-all-odd-length-subarrays/"
    },
    {
        "name": "Richest Customer Wealth",
        "tags": [
            "array",
            "wealth calculation",
            "element sum",
            "richness comparison"
        ],
        "platforms": [
            "LeetCode"
        ],
        "level": "Easy",
        "link": "https://leetcode.com/problems/richest-customer-wealth/"
    },
    {
        "name": "Intersection of Two Arrays II",
        "tags": [
            "array",
            "hash table",
            "sorting",
            "intersection"
        ],
        "platforms": [
            "LeetCode"
        ],
        "level": "Easy",
        "link": "https://leetcode.com/problems/intersection-of-two-arrays-ii/"
    },
    {
        "name": "Remove Duplicates from Sorted Array",
        "tags": [
            "Array",
            "Two Pointers"
        ],
        "platforms": [
            "LeetCode"
        ],
        "level": "Easy",
        "link": "https://leetcode.com/problems/remove-duplicates-from-sorted-array/"
    },
    {
        "name": "Best Time to Buy and Sell Stock II",
        "tags": [
            "array",
            "greedy",
            "max profit calculation",
            "stock trading"
        ],
        "platforms": [
            "LeetCode"
        ],
        "level": "Easy",
        "link": "https://leetcode.com/problems/best-time-to-buy-and-sell-stock-ii/"
    },
    {
        "name": "Reverse Integer",
        "tags": [
            "math"
        ],
        "platforms": [
            "LeetCode"
        ],
        "level": "Easy",
        "link": "https://leetcode.com/problems/reverse-integer/"
    },
    {
        "name": "Jump Game",
        "tags": [
            "array",
            "greedy",
            "dp",
            "jump game"
        ],
        "platforms": [
            "LeetCode"
        ],
        "level": "Medium",
        "link": "https://leetcode.com/problems/jump-game/"
    },
    {
        "name": "Palindrome Partitioning",
        "tags": [
            "backtracking",
            "string",
            "partitioning",
            "palindrome"
        ],
        "platforms": [
            "LeetCode"
        ],
        "level": "Medium",
        "link": "https://leetcode.com/problems/palindrome-partitioning/"
    },
    {
        "name": "No Strings Attached",
        "tags": [
            "data structure",
            "dp",
            "algorithm"
        ],
        "platforms": [
            "Codechef"
        ],
        "level": "Medium",
        "link": "https://www.codechef.com/problems/NSA"
    },
    {
        "name": "Maximise Islands",
        "tags": [
            "data structure",
            "bruteforce",
            "algorithm"
        ],
        "platforms": [
            "Codechef"
        ],
        "level": "Medium",
        "link": "https://www.codechef.com/problems/MINIL"
    },
    {
        "name": "Points in Segments",
        "tags": [
            "data structure"
        ],
        "platforms": [
            "LightOJ"
        ],
        "level": "Medium",
        "link": "https://lightoj.com/problem/points-in-segments-ii"
    },
    {
        "name": "Magic Trick",
        "tags": [
            "math",
            "data structure",
            "algorithm"
        ],
        "platforms": [
            "Codechef"
        ],
        "level": "Medium",
        "link": "https://www.codechef.com/problems/MTRICK"
    },
    {
        "name": "Jogging Trails",
        "tags": [
            "graph"
        ],
        "platforms": [
            "LightOJ"
        ],
        "level": "Medium",
        "link": "https://lightoj.com/problem/jogging-trails"
    },
    {
        "name": "String",
        "tags": [
            "implementation",
            "math",
            "strings"
        ],
        "platforms": [
            "Codeforces"
        ],
        "level": "Hard",
        "link": "https://codeforces.com/problemset/problem/128/C"
    },
    {
        "name": "Longest Valid Parentheses",
        "tags": [
            "string",
            "stack",
            "dp",
            "parentheses"
        ],
        "platforms": [
            "LeetCode"
        ],
        "level": "Hard",
        "link": "https://leetcode.com/problems/longest-valid-parentheses/"
    },
    {
        "name": "Diagonal Sum",
        "tags": [
            "greedy"
        ],
        "platforms": [
            "LightOJ"
        ],
        "level": "Hard",
        "link": "https://lightoj.com/problem/diagonal-sum"
    },
    {
        "name": "Trapping Rain Water",
        "tags": [
            "array",
            "two pointers",
            "stack",
            "water trapping"
        ],
        "platforms": [
            "LeetCode"
        ],
        "level": "Hard",
        "link": "https://leetcode.com/problems/trapping-rain-water/"
    },
    {
        "name": "Palindrome Partitioning II",
        "tags": [
            "string",
            "dp",
            "backtracking",
            "palindrome"
        ],
        "platforms": [
            "LeetCode"
        ],
        "level": "Hard",
        "link": "https://leetcode.com/problems/palindrome-partitioning-ii/"
    },
    {
        "name": "Minimum Window Substring",
        "tags": [
            "string",
            "two pointers",
            "sliding window",
            "substring"
        ],
        "platforms": [
            "LeetCode"
        ],
        "level": "Hard",
        "link": "https://leetcode.com/problems/minimum-window-substring/"
    },
    {
        "name": "Increasing Addition",
        "tags": [
            "data structure",
            "math",
            "adhoc",
            "algorithm",
            "constructive"
        ],
        "platforms": [
            "Codechef"
        ],
        "level": "Hard",
        "link": "https://www.codechef.com/problems/INCADD"
    },
    {
        "name": "Distance in Tree",
        "tags": [
            "dfs and similar",
            "graph",
            "trees"
        ],
        "platforms": [
            "Codeforces"
        ],
        "level": "Hard",
        "link": "https://codeforces.com/problemset/problem/161/D"
    },
    {
        "name": "Minimum Window Substring",
        "tags": [
            "string",
            "hash table",
            "two pointers",
            "substring"
        ],
        "platforms": [
            "LeetCode"
        ],
        "level": "Hard",
        "link": "https://leetcode.com/problems/minimum-window-substring/"
    },
    {
        "name": "Trapping Rain Water",
        "tags": [
            "array",
            "two pointers",
            "stack",
            "water trapping"
        ],
        "platforms": [
            "LeetCode"
        ],
        "level": "Hard",
        "link": "https://leetcode.com/problems/trapping-rain-water/"
    },
    {
        "name": "Sherlock and the Ugly Flower",
        "tags": [
            "data structure",
            "math",
            "algorithm",
            "searching"
        ],
        "platforms": [
            "Codechef"
        ],
        "level": "Hard",
        "link": "https://www.codechef.com/problems/UGLYF"
    },
    {
        "name": "ChefGame",
        "tags": [
            "data structure",
            "graph"
        ],
        "platforms": [
            "Codechef"
        ],
        "level": "Hard",
        "link": "https://www.codechef.com/problems/CHEFGAME"
    },
    {
        "name": "First Missing Positive",
        "tags": [
            "array",
            "hash table",
            "positive numbers",
            "missing"
        ],
        "platforms": [
            "LeetCode"
        ],
        "level": "Hard",
        "link": "https://leetcode.com/problems/first-missing-positive/"
    },
    {
        "name": "Regular Expression Matching",
        "tags": [
            "string",
            "dp",
            "backtracking",
            "regular expression"
        ],
        "platforms": [
            "LeetCode"
        ],
        "level": "Hard",
        "link": "https://leetcode.com/problems/regular-expression-matching/"
    },
    {
        "name": "Binary String Game",
        "tags": [
            "data structure",
            "games"
        ],
        "platforms": [
            "Codechef"
        ],
        "level": "Hard",
        "link": "https://www.codechef.com/problems/BINSTRGAME"
    },
    {
        "name": "Underwater Snipers",
        "tags": [
            "greedy"
        ],
        "platforms": [
            "LightOJ"
        ],
        "level": "Hard",
        "link": "https://lightoj.com/problem/underwater-snipers"
    },
    {
        "name": "Bytelandian Shoppers",
        "tags": [
            "combinatorics",
            "math"
        ],
        "platforms": [
            "Codechef"
        ],
        "level": "Hard",
        "link": "https://www.codechef.com/problems/BYTESHOP"
    },
    {
        "name": "Sudoku Solver",
        "tags": [
            "array",
            "backtracking",
            "hash table",
            "sudoku"
        ],
        "platforms": [
            "LeetCode"
        ],
        "level": "Hard",
        "link": "https://leetcode.com/problems/sudoku-solver/"
    }
]