[
    {
        "name": "Word Capitalization",
        "tags": [
            "strings",
            "implementation"
        ],
        "platforms": [
            "Codeforces"
        ],
        "level": "Easy",
        "link": "https://codeforces.com/problemset/problem/281/A"
    },
    {
        "name": "Reverse String",
        "tags": [
            "string",
            "string manipulation",
            "reversal",
            "character handling"
        ],
        "platforms": [
            "LeetCode"
        ],
        "level": "Easy",
        "link": "https://leetcode.com/problems/reverse-string/"
    },
    {
        "name": "Intersection of Two Arrays II",
        "tags": [
            "array",
            "hash table",
            "sorting",
            "intersection"
        ],
        "platforms": [
            "LeetCode"
        ],
        "level": "Easy",
        "link": "https://leetcode.com/problems/intersection-of-two-arrays-ii/"
    },
    {
        "name": "Goal Parser Interpretation",
        "tags": [
            "string",
            "parsing",
            "substring manipulation",
            "symbol interpretation"
        ],
        "platforms": [
            "LeetCode"
        ],
        "level": "Easy",
        "link": "https://leetcode.com/problems/goal-parser-interpretation/"
    },
    {
        "name": "Richest Customer Wealth",
        "tags": [
            "array",
            "wealth calculation",
            "element sum",
            "richness comparison"
        ],
        "platforms": [
            "LeetCode"
        ],
        "level": "Easy",
        "link": "https://leetcode.com/problems/richest-customer-wealth/"
    },
    {
        "name": "Reverse Vowels of a String",
        "tags": [
            "string",
            "two pointers",
            "vowel manipulation",
            "character swapping"
        ],
        "platforms": [
            "LeetCode"
        ],
        "level": "Easy",
        "link": "https://leetcode.com/problems/reverse-vowels-of-a-string/"
    },
    {
        "name": "Merge Sorted Array",
        "tags": [
            "Array",
            "Two Pointers"
        ],
        "platforms": [
            "LeetCode"
        ],
        "level": "Easy",
        "link": "https://leetcode.com/problems/merge-sorted-array/"
    },
    {
        "name": "Merge Sorted Array",
        "tags": [
            "array",
            "two pointers",
            "merge operation",
            "in-place manipulation"
        ],
        "platforms": [
            "LeetCode"
        ],
        "level": "Easy",
        "link": "https://leetcode.com/problems/merge-sorted-array/"
    },
    {
        "name": "Power of Three",
        "tags": [
            "math",
            "number properties",
            "exponentiation",
            "divisibility"
        ],
        "platforms": [
            "LeetCode"
        ],
        "level": "Easy",
        "link": "https://leetcode.com/problems/power-of-three/"
    },
    {
        "name": "How Many Numbers Are Smaller Than the Current Number",
        "tags": [
            "array",
            "sorting",
            "counting",
            "element comparison"
        ],
        "platforms": [
            "LeetCode"
        ],
        "level": "Easy",
        "link": "https://leetcode.com/problems/how-many-numbers-are-smaller-than-the-current-number/"
    },
    {
        "name": "Shiritori",
        "tags": [
            "implementation",
            "strings"
        ],
        "platforms": [
            "AtCoder"
        ],
        "level": "Easy",
        "link": "https://atcoder.jp/contests/abc109/tasks/abc109_b"
    },
    {
        "name": "Two Sum",
        "tags": [
            "arrays",
            "hash table"
        ],
        "platforms": [
            "LeetCode",
            "HackerRank"
        ],
        "level": "Easy",
        "link": "https://leetcode.com/problems/two-sum/"
    },
    {
        "name": "Minimum Path Sum",
        "tags": [
            "Array",
            "dp"
        ],
        "platforms": [
            "LeetCode"
        ],
        "level": "Medium",
        "link": "https://leetcode.com/problems/minimum-path-sum/"
    },
    {
        "name": "Subarray Product Less Than K",
        "tags": [
            "array",
            "two pointers",
            "sliding window",
            "product"
        ],
        "platforms": [
            "LeetCode"
        ],
        "level": "Medium",
        "link": "https://leetcode.com/problems/subarray-product-less-than-k/"
    },
    {
        "name": "Make All Zero",
        "tags": [
            "constructive",
            "adhoc",
            "algorithm"
        ],
        "platforms": [
            "Codechef"
        ],
        "level": "Medium",
        "link": "https://www.codechef.com/problems/MAKE0"
    },
    {
        "name": "Unique Paths",
        "tags": [
            "array",
            "dp",
            "combinatorics",
            "grid"
        ],
        "platforms": [
            "LeetCode"
        ],
        "level": "Medium",
        "link": "https://leetcode.com/problems/unique-paths/"
    },
    {
        "name": "Largest Y",
        "tags": [
            "math",
            "algorithm",
            "bit manipulation"
        ],
        "platforms": [
            "Codechef"
        ],
        "level": "Medium",
        "link": "https://www.codechef.com/problems/LARGESTY"
    },
    {
        "name": "Regular Expression Matching",
        "tags": [
            "String",
            "dp",
            "Backtracking"
        ],
        "platforms": [
            "LeetCode"
        ],
        "level": "Hard",
        "link": "https://leetcode.com/problems/regular-expression-matching/"
    },
    {
        "name": "Minimum Window Substring",
        "tags": [
            "string",
            "two pointers",
            "sliding window",
            "substring"
        ],
        "platforms": [
            "LeetCode"
        ],
        "level": "Hard",
        "link": "https://leetcode.com/problems/minimum-window-substring/"
    },
    {
        "name": "Median of Two Sorted Arrays",
        "tags": [
            "array",
            "binary search",
            "divide and conquer",
            "median"
        ],
        "platforms": [
            "LeetCode"
        ],
        "level": "Hard",
        "link": "https://leetcode.com/problems/median-of-two-sorted-arrays/"
    },
    {
        "name": "Clear the Array",
        "tags": [
            "greedy",
            "sorting"
        ],
        "platforms": [
            "Codechef"
        ],
        "level": "Hard",
        "link": "https://www.codechef.com/problems/CLEARARR"
    },
    {
        "name": "Palindrome Pairs",
        "tags": [
            "string",
            "hash table",
            "trie",
            "palindrome"
        ],
        "platforms": [
            "LeetCode"
        ],
        "level": "Hard",
        "link": "https://leetcode.com/problems/palindrome-pairs/"
    },
    {
        "name": "Chef and Filters",
        "tags": [
            "dp",
            "bit manipulation",
            "data structure",
            "math",
            "algorithm"
        ],
        "platforms": [
            "Codechef"
        ],
        "level": "Hard",
        "link": "https://www.codechef.com/problems/CHEFFILT"
    },
    {
        "name": "Substring with Concatenation of All Words",
        "tags": [
            "string",
            "hash table",
            "substring",
            "concatenation"
        ],
        "platforms": [
            "LeetCode"
        ],
        "level": "Hard",
        "link": "https://leetcode.com/problems/substring-with-concatenation-of-all-words/"
    },
    {
        "name": "Beautiful Regional Contest",
        "tags": [
            "greedy",
            "implementation",
            "sortings"
        ],
        "platforms": [
            "Codeforces"
        ],
        "level": "Hard",
        "link": "https://codeforces.com/problemset/problem/1265/C"
    },
    {
        "name": "Median of Two Sorted Arrays",
        "tags": [
            "Array",
            "Binary Search",
            "Divide and Conquer"
        ],
        "platforms": [
            "LeetCode"
        ],
        "level": "Hard",
        "link": "https://leetcode.com/problems/median-of-two-sorted-arrays/"
    },
    {
        "name": "Useful Number",
        "tags": [
            "math",
            "number theory"
        ],
        "platforms": [
            "Codechef"
        ],
        "level": "Hard",
        "link": "https://www.codechef.com/problems/USF"
    }
]